Workbook
Name _Toc112831755: 'RFS ou RFC'!$B$13
Name Atores: Atores!$B$13:$C$17
Name CUC: 'RFS ou RFC'!$D$13:$D$39
Name FCAMB: Fatores!$G$36
Name FCTEC: Fatores!$E$22
Name ITEC: Fatores!$E$22
Name PTA: Atores!$D$10
Name PTUC: 'RFS ou RFC'!$D$10
Name UC: 'RFS ou RFC'!$A$12:$C$39

Sheet Geral
B3: Estimativa de Esforço de Projeto baseado em Pontos de Caso de Uso (vs 1.1)
B6: Projeto: | D6: <Nome do projeto>
B7: Responsável: | D7: <Nome do responsável pela estimativa>
B8: Data: | D8: <data da estimativa> | F8: Vs. do Documento: | H8: x.x
D9: < Obs.: As instruções para uso da planilha encontram-se logo a baixo>
B12: Resultado da Estimativa | G12: Esforço por fases | J12: Horas | K12: %
B13: Total de Pontos de Caso de Uso(tamanho) | E13: =(Atores!D10+'RFS ou RFC'!D10)*Fatores!E22*Fatores!G36 -> 96.5006 | G13: Fase de Prospecção | J13: =$E$13*$E$14*K13 -> 13.510084 | K13: =dadoshistoricos!E31 -> 0.046666667
B14: Homens/hora por RFS | E14: 3 | G14: Fase de Análise | J14: =$E$13*$E$14*K14 -> 47.606963 | K14: =dadoshistoricos!F31*0.8 -> 0.16444444
G15: Fase de Projeto | J15: =$E$13*$E$14*K15 -> 11.901741 | K15: =dadoshistoricos!F31*0.2 -> 0.041111111
G16: Fase de Planejamento | J16: =$E$13*$E$14*K16 -> 19.30012 | K16: =dadoshistoricos!G31 -> 0.066666667
G17: Fase de Desenvolvimento | J17: =$E$13*$E$14*K17 -> 160.83433 | K17: =dadoshistoricos!H31 -> 0.55555556
G18: Processo de Monitoramento e Controle | J18: =$E$13*$E$14*K18 -> 6.4333733 | K18: =dadoshistoricos!I31 -> 0.022222222
G19: Fase de Fechamento | J19: =$E$13*$E$14*K19 -> 19.621789 | K19: =dadoshistoricos!J31 -> 0.067777778
B20: Instruções para realizar a estimativa do Projeto: | G20: Processo Controle de mudanças | J20: =$E$13*$E$14*K20 -> 10.293397 | K20: =dadoshistoricos!K31 -> 0.035555556
G21: Total de horas do Projeto | J21: =SUM(J13:J20) -> 289.5018 | K21: =SUM(K13:K20) -> 1
B22: 1) Preencha a Planilha Atores indicando os atores(usuários do sistema) e a sua complexidade.
B23: 2) Preencha a Planilha RFS ou RFC indicando os Requisitos e quantidade de transações.
B24: 3) Preencha a Planilha Fatores, com os fatores de complexidade ambiental e técnicos do Projeto.
B25: 4) Após a execução dos passos anteriores, os resultados finais encontram-se na Planilha Geral.
B27: Obs.:
B28: Existem informações ocultas na células que possuem marcação(pontos coloridos). Posicione o mouse sobre a celula para visualizar a informação.

Sheet Atores
B2: Atores do Projeto
B6: Complexidade do Ator | C6: Peso | D6: Qt. de Atores
B7: Simples | C7: 1 | D7: =COUNTIF(Atores,B7) -> 0
B8: Médio | C8: 2 | D8: =COUNTIF(Atores,B8) -> 0
B9: Complexo | C9: 3 | D9: =COUNTIF(Atores,B9) -> 3
C10: Peso Total Atores = | D10: =(C7*D7)+(C8*D8)+(C9*D9) -> 9
B13: Atores | C13: Complexidade
B14: Administrador | C14: Complexo
B15: Corretor | C15: Complexo
B16: Cliente | C16: Complexo
B18: Total | C18: =D10 -> 9

Sheet RFS ou RFC
B2: Casos de Uso do Projeto
B6: Complexidade do RF | C6: Peso | D6: Qt. de UC
B7: Simples | C7: 3 | D7: =COUNTIF(CUC,B7) -> 19
B8: Médio | C8: 4 | D8: =COUNTIF(CUC,B8) -> 8
B9: Complexo | C9: 5 | D9: =COUNTIF(CUC,B9) -> 0
C10: Peso Total UC | D10: =(C7*D7)+(C8*D8)+(C9*D9) -> 89
A12: ID | B12: Nome do RFC ou RFS | C12: Nro Entidades | D12: Complexidade | E12: Discriminar Transações(opcional)
A13: [RFC01] | B13: Manter Usuários | C13: 2 | D13: =IF(C13<4,"Simples",(IF(C13>5,"Complexo","Médio"))) -> Simples | E13: Cadastro, consulta, edição e remoção de usuários (Administrador, Corretor, Cliente). Exclusão bloqueada se contrato ativo. | O13: 1
A14: [RFC02] | B14: Manter Imóveis | C14: 3 | D14: =IF(C14<4,"Simples",(IF(C14>5,"Complexo","Médio"))) -> Simples | E14: Cadastro, consulta, edição e remoção de imóveis com dados completos (endereço, tipo, valor, status). | O14: 2
A15: [RFC03] | B15: Manter Contratos | C15: 4 | D15: =IF(C15<4,"Simples",(IF(C15>5,"Complexo","Médio"))) -> Médio | E15: Cadastro, consulta, edição e remoção de contratos (locação ou venda) vinculando imóveis e clientes. Exclusão com pagamentos bloqueada. | O15: 3
A16: [RFC04] | B16: Manter Pagamentos/Recebimentos | C16: 3 | D16: =IF(C16<4,"Simples",(IF(C16>5,"Complexo","Médio"))) -> Simples | E16: Cadastro, consulta, edição e remoção de pagamentos, repasses e comissões. Exclusão bloqueada se confirmado como 'Pago'. | O16: 4
A17: [RFC05] | B17: Gerar Relatórios e Indicadores | C17: 5 | D17: =IF(C17<4,"Simples",(IF(C17>5,"Complexo","Médio"))) -> Médio | E17: Geração de relatórios e indicadores financeiros e de operações (imóveis, contratos, pagamentos). | O17: 5
A18: [RFC06] | B18: Gerenciar Documentos Associados | C18: 4 | D18: =IF(C18<4,"Simples",(IF(C18>5,"Complexo","Médio"))) -> Médio | E18: Upload, download e visualização de documentos eletrônicos associados às entidades. | O18: 6
A19: [RFC07] | B19: Autenticar e gerir acesso | C19: 4 | D19: =IF(C19<4,"Simples",(IF(C19>5,"Complexo","Médio"))) -> Médio | E19: Login seguro, controle de permissões baseado em perfil de usuário. | O19: 7
A20: [RFS01] | B20: Cadastrar Usuário | C20: 1 | D20: =IF(C20<4,"Simples",(IF(C20>5,"Complexo","Médio"))) -> Simples | E20: Preencher campos de cadastro de usuário (Nome, CPF/CNPJ, E-mail, Telefone, Perfil, Senha). | O20: 8
A21: [RFS02] | B21: Editar Usuário | C21: 1 | D21: =IF(C21<4,"Simples",(IF(C21>5,"Complexo","Médio"))) -> Simples | E21: Editar atributos de usuário; usuários podem editar alguns dados pessoais; atualização em todas as menções. | O21: 9
A22: [RFS03] | B22: Remover Usuário | C22: 2 | D22: =IF(C22<4,"Simples",(IF(C22>5,"Complexo","Médio"))) -> Simples | E22: Remoção lógica com bloqueio se dependências (contratos) existirem; mensagem de erro. | O22: 10
A23: [RFS04] | B23: Consultar Usuário | C23: 1 | D23: =IF(C23<4,"Simples",(IF(C23>5,"Complexo","Médio"))) -> Simples | E23: Pesquisa por nome com filtros; ordenação alfabética; exibir resultados. | O23: 11
A24: [RFS05] | B24: Cadastrar Imóvel | C24: 2 | D24: =IF(C24<4,"Simples",(IF(C24>5,"Complexo","Médio"))) -> Simples | E24: Preencher campos do imóvel (endereço, tipo, finalidade, valor, status, área, quartos...). | O24: 12
... A53: [RNF08] | B53: Estrutura Modular | C53: 2 | D53: =IF(C53<4,"Simples",(IF(C53>5,"Complexo","Médio"))) -> Simples | E53: Arquitetura modular para permitir evolução e novos módulos. | O53: 42
O54: 43
O55: 44
O56: 45
O57: 46
O58: 47
O59: 48
A60: Total | B60: =SUBTOTAL(103,B13:B59) -> 41 | O60: 49
O61: 50
O62: 51
O63: 52
O64: 53
O65: 54
O66: 55
O67: 56
O68: 57
O69: 58
O70: 59
O71: 60
O72: 61
... O1010: 999

Sheet Fatores
B4: Fatores de Complexidade
B7: Influência Tecnológica
B8: ID | C8: Descrição | D8: Peso | E8: Influência
B9: T01 | C9: Sistemas Distribuídos | D9: 2 | E9: 0
B10: T02 | C10: Tempo de resposta | D10: 1 | E10: 2
B11: T03 | C11: Grau de escolaridade do usuário final | D11: 1 | E11: 1
B12: T04 | C12: Processamento interno complexo | D12: 1 | E12: 0
B13: T05 | C13: Reusabilidade do código em outras aplicações | D13: 1 | E13: 0
B14: T06 | C14: Facilidade de instalação | D14: 0.5 | E14: 5
B15: T07 | C15: Usabilidade (facilidade operacional) | D15: 0.5 | E15: 5
B16: T08 | C16: Portabilidade | D16: 2 | E16: 4
B17: T09 | C17: Facilidade de manutenção | D17: 1 | E17: 5
B18: T10 | C18: Concorrência | D18: 1 | E18: 0
B19: T11 | C19: Características especiais de segurança | D19: 1 | E19: 5
B20: T12 | C20: Acesso direto para terceiros | D20: 1 | E20: 0
B21: T13 | C21: Facilidades especiais de treinamento | D21: 1 | E21: 0
B22: Fator de Complexidade Técnica | E22: =0.6+(0.01*SUM(D9*E9,D10*E10,D11*E11,D12*E12,D13*E13,D14*E14,D15*E15,D16*E16,D17*E17,D18*E18,D19*E19,D20*E20,D21*E21)) -> 0.86
B26: Influência Ambiental
B27: ID | C27: Descrição | F27: Peso | G27: Influência
B28: F01 | C28: Familiaridade com o Processo de Desenvolvimento de Software | F28: 1.5 | G28: 1
B29: F02 | C29: Experiência na Aplicação | F29: 0.5 | G29: 0
B30: F03 | C30: Experiência em Programação Orientada a Objetos | F30: 1 | G30: 2
B31: F04 | C31: Capacidade do Líder de Projeto | F31: 0.5 | G31: 0
B32: F05 | C32: Motivação | F32: 1 | G32: 3
B33: F06 | C33: Requisitos estáveis | F33: 2 | G33: 5
B34: F07 | C34: Trabalhadores com dedicação parcial | F34: -1 | G34: 5
B35: F08 | C35: Dificuldade da Linguagem de Programação | F35: -1 | G35: 3
B36: Fator de Complexidade Ambiental | G36: =1.4+(-0.03*SUM(F28*G28,F29*G29,F30*G30,F31*G31,F32*G32,F33*G33,F34*G34,F35*G35)) -> 1.145

Sheet dadoshistoricos
B1: Base histórica de Projetos
B5: Projetos | C5: Tamanho | D5: Horas Reais | E5: Prospecção | F5: Análise e Projeto | G5: Planejamento | H5: Desenvolvimento | I5: Fechamento | J5: Mon.Controle | K5: Cont. Mud. | L5: Produtividade
B6: Projeto 01 | C6: 190 | D6: =SUM(E6:K6) -> 589 | E6: 25 | F6: 80 | G6: 25 | H6: 400 | I6: 10 | J6: 25 | K6: 24 | L6: =D6/C6 -> 3.1
B7: Projeto 02 | C7: 130 | D7: =SUM(E7:K7) -> 326 | E7: 20 | F7: 120 | G7: 30 | H7: 100 | I7: 10 | J7: 30 | K7: 16 | L7: =D7/C7 -> 2.5076923
B8: Projeto 03 | C8: 140 | D8: =SUM(E8:K8) -> 399 | E8: 17 | F8: 90 | G8: 32 | H8: 200 | I8: 12 | J8: 32 | K8: 16 | L8: =D8/C8 -> 2.85
B9: Projeto 04 | C9: 125 | D9: =SUM(E9:K9) -> 486 | E9: 22 | F9: 80 | G9: 33 | H9: 300 | I9: 8 | J9: 35 | K9: 8 | L9: =D9/C9 -> 3.888
B29: Total de horas por fase | D29: =SUM(D6:D28) -> 1800 | E29: =SUM(E6:E28) -> 84 | F29: =SUM(F6:F28) -> 370 | G29: =SUM(G6:G28) -> 120 | H29: =SUM(H6:H28) -> 1000 | I29: =SUM(I6:I28) -> 40 | J29: =SUM(J6:J28) -> 122 | K29: =SUM(K6:K28) -> 64
J30: Produtividade média | L30: 8
B31: % de esforço por fases | E31: =(E29*1)/$D$29 -> 0.046666667 | F31: =(F29*1)/$D$29 -> 0.20555556 | G31: =(G29*1)/$D$29 -> 0.066666667 | H31: =(H29*1)/$D$29 -> 0.55555556 | I31: =(I29*1)/$D$29 -> 0.022222222 | J31: =(J29*1)/$D$29 -> 0.067777778 | K31: =(K29*1)/$D$29 -> 0.035555556 | L31: =SUM(E31:K31) -> 1
